LICENSE
taxtea/__init__.py
taxtea/admin.py
taxtea/apps.py
taxtea/checks.py
taxtea/exceptions.py
taxtea/fixtures/states.json
taxtea/migrations/0001_initial.py
taxtea/migrations/0002_auto_20200421_2250.py
taxtea/migrations/0003_auto_20200804_1356.py
taxtea/migrations/__init__.py
taxtea/models.py
taxtea/services/__init__.py
taxtea/services/avalara.py
taxtea/services/usps.py
taxtea/settings.py
django_taxtea-1.0.2.dist-info/entry_points.txt
django_taxtea-1.0.2.dist-info/LICENSE
django_taxtea-1.0.2.dist-info/WHEEL
django_taxtea-1.0.2.dist-info/METADATA
django_taxtea-1.0.2.dist-info/RECORD
