Metadata-Version: 2.1
Name: django-taxtea
Version: 1.0.2
Summary: TaxTea - Django App that calculates tax rates for SaaS products
Home-page: https://github.com/lowercase-app/django-taxtea
License: MIT
Keywords: django,tax,stripe,SaaS
Author: Matt Strayer
Author-email: git@mattstrayer.com
Requires-Python: >=3.6.0,<4.0.0
Classifier: Development Status :: 5 - Production/Stable
Classifier: Environment :: Web Environment
Classifier: Framework :: Django
Classifier: Framework :: Django :: 2.2
Classifier: Framework :: Django :: 3.0
Classifier: Intended Audience :: Developers
Classifier: License :: OSI Approved :: MIT License
Classifier: Programming Language :: Python
Classifier: Programming Language :: Python :: 3
Classifier: Programming Language :: Python :: 3 :: Only
Classifier: Programming Language :: Python :: 3.6
Classifier: Programming Language :: Python :: 3.7
Classifier: Programming Language :: Python :: 3.8
Classifier: Topic :: Office/Business :: Financial
Classifier: Topic :: Software Development :: Libraries :: Python Modules
Requires-Dist: django (>=3.0.5,<4.0.0)
Requires-Dist: django-localflavor (>=3.0.1,<4.0.0)
Requires-Dist: httpx (>=0.13.3,<0.14.0)
Requires-Dist: xmltodict (>=0.12.0,<0.13.0)
Project-URL: Documentation, https://www.djangotaxtea.com/
Project-URL: Repository, https://github.com/lowercase-app/django-taxtea
